routex/__init__.py
routex-0.1.0.dist-info/licenses/LICENSE
tests/__init__.py
routex-0.1.0.dist-info/METADATA
routex-0.1.0.dist-info/WHEEL
routex-0.1.0.dist-info/top_level.txt
routex-0.1.0.dist-info/RECORD
