Metadata-Version: 2.4
Name: RouteX
Version: 0.1.0
Summary: A python toolkit for generarting routing problem instances
Home-page: https://github.com/INTELLIGENTICA/RouteX
Author: Abdelouahed Ben Mhamed
Author-email: Abdelouahed Ben Mhamed <abdelouahed.benmhamed@um6p.ma>
License: MIT
Project-URL: Homepage, https://github.com/INTELLIGENTICA/RouteX
Requires-Python: >=3.7
License-File: LICENSE
Dynamic: author
Dynamic: home-page
Dynamic: license-file
Dynamic: requires-python
